{
  "as_of": "2026-07-13",
  "generated_at": "2026-07-13T22:03:10+00:00",
  "data_source": "yfinance",
  "currency": "USD",
  "periods": [
    "1D",
    "1W",
    "1M",
    "3M",
    "6M",
    "YTD",
    "1Y"
  ],
  "total_return_periods": [
    "1Y"
  ],
  "coverage": {
    "ok": 47,
    "no_data": 0,
    "total": 47
  },
  "disclaimer": "情報提供目的であり投資助言ではありません。",
  "blocks": [
    {
      "id": "us_index",
      "title": "主要米国株価指数 ETF",
      "items": [
        {
          "label": "ダウ平均",
          "ticker": "DIA",
          "review": false,
          "status": "ok",
          "as_of": "2026-07-13",
          "stale": false,
          "returns": {
            "1D": {
              "price": -0.25,
              "total": null
            },
            "1W": {
              "price": -1.06,
              "total": null
            },
            "1M": {
              "price": 2.22,
              "total": null
            },
            "3M": {
              "price": 8.78,
              "total": null
            },
            "6M": {
              "price": 6.61,
              "total": null
            },
            "YTD": {
              "price": 9.13,
              "total": null
            },
            "1Y": {
              "price": 18.24,
              "total": 20.04
            }
          },
          "momentum": {
            "cross": "golden",
            "days_since_cross": 46,
            "sma25": 518.47,
            "sma75": 499.46,
            "rsi": 59.0,
            "rsi_state": "neutral"
          }
        },
        {
          "label": "S&P500",
          "ticker": "SPY",
          "review": false,
          "status": "ok",
          "as_of": "2026-07-13",
          "stale": false,
          "returns": {
            "1D": {
              "price": -0.77,
              "total": null
            },
            "1W": {
              "price": -0.28,
              "total": null
            },
            "1M": {
              "price": 1.0,
              "total": null
            },
            "3M": {
              "price": 9.19,
              "total": null
            },
            "6M": {
              "price": 7.99,
              "total": null
            },
            "YTD": {
              "price": 9.86,
              "total": null
            },
            "1Y": {
              "price": 20.13,
              "total": 21.46
            }
          },
          "momentum": {
            "cross": "golden",
            "days_since_cross": 50,
            "sma25": 742.59,
            "sma75": 722.13,
            "rsi": 54.2,
            "rsi_state": "neutral"
          }
        },
        {
          "label": "ナスダック100",
          "ticker": "QQQ",
          "review": false,
          "status": "ok",
          "as_of": "2026-07-13",
          "stale": false,
          "returns": {
            "1D": {
              "price": -1.9,
              "total": null
            },
            "1W": {
              "price": -1.53,
              "total": null
            },
            "1M": {
              "price": -1.33,
              "total": null
            },
            "3M": {
              "price": 15.28,
              "total": null
            },
            "6M": {
              "price": 13.65,
              "total": null
            },
            "YTD": {
              "price": 15.86,
              "total": null
            },
            "1Y": {
              "price": 28.43,
              "total": 29.05
            }
          },
          "momentum": {
            "cross": "golden",
            "days_since_cross": 52,
            "sma25": 719.43,
            "sma75": 683.45,
            "rsi": 47.7,
            "rsi_state": "neutral"
          }
        },
        {
          "label": "コアS&P中型株",
          "ticker": "IJH",
          "review": false,
          "status": "ok",
          "as_of": "2026-07-13",
          "stale": false,
          "returns": {
            "1D": {
              "price": -0.57,
              "total": null
            },
            "1W": {
              "price": -1.54,
              "total": null
            },
            "1M": {
              "price": -1.05,
              "total": null
            },
            "3M": {
              "price": 5.66,
              "total": null
            },
            "6M": {
              "price": 8.48,
              "total": null
            },
            "YTD": {
              "price": 14.0,
              "total": null
            },
            "1Y": {
              "price": 18.6,
              "total": 20.15
            }
          },
          "momentum": {
            "cross": "golden",
            "days_since_cross": 52,
            "sma25": 75.6,
            "sma75": 73.19,
            "rsi": 49.0,
            "rsi_state": "neutral"
          }
        },
        {
          "label": "コアS&P小型株",
          "ticker": "IJR",
          "review": false,
          "status": "ok",
          "as_of": "2026-07-13",
          "stale": false,
          "returns": {
            "1D": {
              "price": -0.39,
              "total": null
            },
            "1W": {
              "price": -1.24,
              "total": null
            },
            "1M": {
              "price": 0.92,
              "total": null
            },
            "3M": {
              "price": 10.0,
              "total": null
            },
            "6M": {
              "price": 14.6,
              "total": null
            },
            "YTD": {
              "price": 20.64,
              "total": null
            },
            "1Y": {
              "price": 28.51,
              "total": 30.19
            }
          },
          "momentum": {
            "cross": "golden",
            "days_since_cross": 54,
            "sma25": 143.87,
            "sma75": 137.2,
            "rsi": 55.0,
            "rsi_state": "neutral"
          }
        },
        {
          "label": "ラッセル1000",
          "ticker": "IWB",
          "review": false,
          "status": "ok",
          "as_of": "2026-07-13",
          "stale": false,
          "returns": {
            "1D": {
              "price": -0.75,
              "total": null
            },
            "1W": {
              "price": -0.48,
              "total": null
            },
            "1M": {
              "price": 1.08,
              "total": null
            },
            "3M": {
              "price": 9.02,
              "total": null
            },
            "6M": {
              "price": 7.78,
              "total": null
            },
            "YTD": {
              "price": 9.79,
              "total": null
            },
            "1Y": {
              "price": 19.65,
              "total": 20.86
            }
          },
          "momentum": {
            "cross": "golden",
            "days_since_cross": 49,
            "sma25": 406.37,
            "sma75": 394.92,
            "rsi": 54.5,
            "rsi_state": "neutral"
          }
        },
        {
          "label": "ラッセル2000",
          "ticker": "IWM",
          "review": false,
          "status": "ok",
          "as_of": "2026-07-13",
          "stale": false,
          "returns": {
            "1D": {
              "price": -0.85,
              "total": null
            },
            "1W": {
              "price": -1.81,
              "total": null
            },
            "1M": {
              "price": 0.18,
              "total": null
            },
            "3M": {
              "price": 10.72,
              "total": null
            },
            "6M": {
              "price": 12.29,
              "total": null
            },
            "YTD": {
              "price": 19.22,
              "total": null
            },
            "1Y": {
              "price": 32.38,
              "total": 33.75
            }
          },
          "momentum": {
            "cross": "golden",
            "days_since_cross": 52,
            "sma25": 293.96,
            "sma75": 280.33,
            "rsi": 49.9,
            "rsi_state": "neutral"
          }
        },
        {
          "label": "ラッセル3000",
          "ticker": "IWV",
          "review": false,
          "status": "ok",
          "as_of": "2026-07-13",
          "stale": false,
          "returns": {
            "1D": {
              "price": -0.72,
              "total": null
            },
            "1W": {
              "price": -0.46,
              "total": null
            },
            "1M": {
              "price": 1.05,
              "total": null
            },
            "3M": {
              "price": 9.09,
              "total": null
            },
            "6M": {
              "price": 8.05,
              "total": null
            },
            "YTD": {
              "price": 10.24,
              "total": null
            },
            "1Y": {
              "price": 20.27,
              "total": 21.42
            }
          },
          "momentum": {
            "cross": "golden",
            "days_since_cross": 50,
            "sma25": 422.83,
            "sma75": 410.57,
            "rsi": 54.5,
            "rsi_state": "neutral"
          }
        },
        {
          "label": "S&P500グロース",
          "ticker": "IVW",
          "review": false,
          "status": "ok",
          "as_of": "2026-07-13",
          "stale": false,
          "returns": {
            "1D": {
              "price": -1.54,
              "total": null
            },
            "1W": {
              "price": -0.48,
              "total": null
            },
            "1M": {
              "price": 1.08,
              "total": null
            },
            "3M": {
              "price": 11.7,
              "total": null
            },
            "6M": {
              "price": 9.28,
              "total": null
            },
            "YTD": {
              "price": 10.71,
              "total": null
            },
            "1Y": {
              "price": 23.27,
              "total": 23.76
            }
          },
          "momentum": {
            "cross": "golden",
            "days_since_cross": 51,
            "sma25": 135.72,
            "sma75": 131.2,
            "rsi": 51.1,
            "rsi_state": "neutral"
          }
        },
        {
          "label": "中型株400グロース",
          "ticker": "IJK",
          "review": false,
          "status": "ok",
          "as_of": "2026-07-13",
          "stale": false,
          "returns": {
            "1D": {
              "price": -1.06,
              "total": null
            },
            "1W": {
              "price": -2.63,
              "total": null
            },
            "1M": {
              "price": -1.77,
              "total": null
            },
            "3M": {
              "price": 5.73,
              "total": null
            },
            "6M": {
              "price": 10.3,
              "total": null
            },
            "YTD": {
              "price": 16.54,
              "total": null
            },
            "1Y": {
              "price": 22.38,
              "total": 23.12
            }
          },
          "momentum": {
            "cross": "golden",
            "days_since_cross": 57,
            "sma25": 114.62,
            "sma75": 110.69,
            "rsi": 45.3,
            "rsi_state": "neutral"
          }
        },
        {
          "label": "小型株600グロース",
          "ticker": "IJT",
          "review": false,
          "status": "ok",
          "as_of": "2026-07-13",
          "stale": false,
          "returns": {
            "1D": {
              "price": -1.0,
              "total": null
            },
            "1W": {
              "price": -2.47,
              "total": null
            },
            "1M": {
              "price": 2.08,
              "total": null
            },
            "3M": {
              "price": 11.19,
              "total": null
            },
            "6M": {
              "price": 16.36,
              "total": null
            },
            "YTD": {
              "price": 22.24,
              "total": null
            },
            "1Y": {
              "price": 26.96,
              "total": 28.0
            }
          },
          "momentum": {
            "cross": "golden",
            "days_since_cross": 55,
            "sma25": 171.44,
            "sma75": 162.16,
            "rsi": 53.0,
            "rsi_state": "neutral"
          }
        },
        {
          "label": "S&P500バリュー",
          "ticker": "IVE",
          "review": false,
          "status": "ok",
          "as_of": "2026-07-13",
          "stale": false,
          "returns": {
            "1D": {
              "price": 0.17,
              "total": null
            },
            "1W": {
              "price": -0.01,
              "total": null
            },
            "1M": {
              "price": 0.94,
              "total": null
            },
            "3M": {
              "price": 6.34,
              "total": null
            },
            "6M": {
              "price": 6.51,
              "total": null
            },
            "YTD": {
              "price": 8.87,
              "total": null
            },
            "1Y": {
              "price": 16.67,
              "total": 18.62
            }
          },
          "momentum": {
            "cross": "golden",
            "days_since_cross": 47,
            "sma25": 227.82,
            "sma75": 223.15,
            "rsi": 62.7,
            "rsi_state": "neutral"
          }
        },
        {
          "label": "中型株400バリュー",
          "ticker": "IJJ",
          "review": false,
          "status": "ok",
          "as_of": "2026-07-13",
          "stale": false,
          "returns": {
            "1D": {
              "price": -0.05,
              "total": null
            },
            "1W": {
              "price": -0.42,
              "total": null
            },
            "1M": {
              "price": -0.27,
              "total": null
            },
            "3M": {
              "price": 5.52,
              "total": null
            },
            "6M": {
              "price": 6.61,
              "total": null
            },
            "YTD": {
              "price": 11.25,
              "total": null
            },
            "1Y": {
              "price": 14.82,
              "total": 16.82
            }
          },
          "momentum": {
            "cross": "golden",
            "days_since_cross": 49,
            "sma25": 145.54,
            "sma75": 141.29,
            "rsi": 55.5,
            "rsi_state": "neutral"
          }
        },
        {
          "label": "小型株600バリュー",
          "ticker": "IJS",
          "review": false,
          "status": "ok",
          "as_of": "2026-07-13",
          "stale": false,
          "returns": {
            "1D": {
              "price": 0.13,
              "total": null
            },
            "1W": {
              "price": -0.15,
              "total": null
            },
            "1M": {
              "price": -0.21,
              "total": null
            },
            "3M": {
              "price": 8.67,
              "total": null
            },
            "6M": {
              "price": 12.77,
              "total": null
            },
            "YTD": {
              "price": 18.86,
              "total": null
            },
            "1Y": {
              "price": 30.33,
              "total": 32.31
            }
          },
          "momentum": {
            "cross": "golden",
            "days_since_cross": 53,
            "sma25": 134.05,
            "sma75": 128.87,
            "rsi": 55.9,
            "rsi_state": "neutral"
          }
        },
        {
          "label": "ダウ配当株100",
          "ticker": "SCHD",
          "review": false,
          "status": "ok",
          "as_of": "2026-07-13",
          "stale": false,
          "returns": {
            "1D": {
              "price": 0.49,
              "total": null
            },
            "1W": {
              "price": 0.99,
              "total": null
            },
            "1M": {
              "price": -0.79,
              "total": null
            },
            "3M": {
              "price": 5.92,
              "total": null
            },
            "6M": {
              "price": 13.77,
              "total": null
            },
            "YTD": {
              "price": 18.7,
              "total": null
            },
            "1Y": {
              "price": 19.14,
              "total": 23.51
            }
          },
          "momentum": {
            "cross": "golden",
            "days_since_cross": 144,
            "sma25": 32.22,
            "sma75": 31.71,
            "rsi": 57.3,
            "rsi_state": "neutral"
          }
        },
        {
          "label": "S&P均等ウェイト",
          "ticker": "RSP",
          "review": false,
          "status": "ok",
          "as_of": "2026-07-13",
          "stale": false,
          "returns": {
            "1D": {
              "price": -0.03,
              "total": null
            },
            "1W": {
              "price": -0.36,
              "total": null
            },
            "1M": {
              "price": 1.22,
              "total": null
            },
            "3M": {
              "price": 7.75,
              "total": null
            },
            "6M": {
              "price": 8.32,
              "total": null
            },
            "YTD": {
              "price": 11.83,
              "total": null
            },
            "1Y": {
              "price": 16.16,
              "total": 18.09
            }
          },
          "momentum": {
            "cross": "golden",
            "days_since_cross": 47,
            "sma25": 211.42,
            "sma75": 204.7,
            "rsi": 59.8,
            "rsi_state": "neutral"
          }
        },
        {
          "label": "モメンタム株",
          "ticker": "MTUM",
          "review": false,
          "status": "ok",
          "as_of": "2026-07-13",
          "stale": false,
          "returns": {
            "1D": {
              "price": -2.22,
              "total": null
            },
            "1W": {
              "price": -2.2,
              "total": null
            },
            "1M": {
              "price": -3.01,
              "total": null
            },
            "3M": {
              "price": 18.26,
              "total": null
            },
            "6M": {
              "price": 21.52,
              "total": null
            },
            "YTD": {
              "price": 25.7,
              "total": null
            },
            "1Y": {
              "price": 33.18,
              "total": 34.12
            }
          },
          "momentum": {
            "cross": "golden",
            "days_since_cross": 56,
            "sma25": 324.26,
            "sma75": 296.6,
            "rsi": 46.7,
            "rsi_state": "neutral"
          }
        },
        {
          "label": "低ボラティリティ株",
          "ticker": "USMV",
          "review": false,
          "status": "ok",
          "as_of": "2026-07-13",
          "stale": false,
          "returns": {
            "1D": {
              "price": 0.06,
              "total": null
            },
            "1W": {
              "price": -0.07,
              "total": null
            },
            "1M": {
              "price": 1.84,
              "total": null
            },
            "3M": {
              "price": 4.61,
              "total": null
            },
            "6M": {
              "price": 3.75,
              "total": null
            },
            "YTD": {
              "price": 3.89,
              "total": null
            },
            "1Y": {
              "price": 5.48,
              "total": 7.1
            }
          },
          "momentum": {
            "cross": "golden",
            "days_since_cross": 31,
            "sma25": 96.14,
            "sma75": 95.02,
            "rsi": 63.7,
            "rsi_state": "neutral"
          }
        }
      ]
    },
    {
      "id": "sectors",
      "title": "S&P500 セクター ETF",
      "items": [
        {
          "label": "一般消費財",
          "ticker": "XLY",
          "review": false,
          "status": "ok",
          "as_of": "2026-07-13",
          "stale": false,
          "returns": {
            "1D": {
              "price": -1.02,
              "total": null
            },
            "1W": {
              "price": -1.67,
              "total": null
            },
            "1M": {
              "price": -0.48,
              "total": null
            },
            "3M": {
              "price": 1.86,
              "total": null
            },
            "6M": {
              "price": -6.58,
              "total": null
            },
            "YTD": {
              "price": -2.82,
              "total": null
            },
            "1Y": {
              "price": 4.81,
              "total": 5.62
            }
          },
          "momentum": {
            "cross": "dead",
            "days_since_cross": 0,
            "sma25": 116.16,
            "sma75": 116.17,
            "rsi": 48.1,
            "rsi_state": "neutral"
          }
        },
        {
          "label": "生活必需品",
          "ticker": "XLP",
          "review": false,
          "status": "ok",
          "as_of": "2026-07-13",
          "stale": false,
          "returns": {
            "1D": {
              "price": 0.56,
              "total": null
            },
            "1W": {
              "price": 0.58,
              "total": null
            },
            "1M": {
              "price": -1.43,
              "total": null
            },
            "3M": {
              "price": 3.73,
              "total": null
            },
            "6M": {
              "price": 4.29,
              "total": null
            },
            "YTD": {
              "price": 8.9,
              "total": null
            },
            "1Y": {
              "price": 4.68,
              "total": 7.58
            }
          },
          "momentum": {
            "cross": "golden",
            "days_since_cross": 25,
            "sma25": 84.21,
            "sma75": 83.47,
            "rsi": 52.5,
            "rsi_state": "neutral"
          }
        },
        {
          "label": "エネルギー",
          "ticker": "XLE",
          "review": false,
          "status": "ok",
          "as_of": "2026-07-13",
          "stale": false,
          "returns": {
            "1D": {
              "price": 3.01,
              "total": null
            },
            "1W": {
              "price": 6.79,
              "total": null
            },
            "1M": {
              "price": -1.41,
              "total": null
            },
            "3M": {
              "price": -0.65,
              "total": null
            },
            "6M": {
              "price": 20.72,
              "total": null
            },
            "YTD": {
              "price": 26.91,
              "total": null
            },
            "1Y": {
              "price": 27.32,
              "total": 31.29
            }
          },
          "momentum": {
            "cross": "dead",
            "days_since_cross": 16,
            "sma25": 55.14,
            "sma75": 57.19,
            "rsi": 57.8,
            "rsi_state": "neutral"
          }
        },
        {
          "label": "金融",
          "ticker": "XLF",
          "review": false,
          "status": "ok",
          "as_of": "2026-07-13",
          "stale": false,
          "returns": {
            "1D": {
              "price": 0.65,
              "total": null
            },
            "1W": {
              "price": -0.12,
              "total": null
            },
            "1M": {
              "price": 5.12,
              "total": null
            },
            "3M": {
              "price": 8.54,
              "total": null
            },
            "6M": {
              "price": 3.39,
              "total": null
            },
            "YTD": {
              "price": 2.37,
              "total": null
            },
            "1Y": {
              "price": 7.5,
              "total": 9.16
            }
          },
          "momentum": {
            "cross": "golden",
            "days_since_cross": 45,
            "sma25": 54.04,
            "sma75": 52.15,
            "rsi": 67.9,
            "rsi_state": "neutral"
          }
        },
        {
          "label": "ヘルスケア",
          "ticker": "XLV",
          "review": false,
          "status": "ok",
          "as_of": "2026-07-13",
          "stale": false,
          "returns": {
            "1D": {
              "price": 0.35,
              "total": null
            },
            "1W": {
              "price": -0.34,
              "total": null
            },
            "1M": {
              "price": 4.94,
              "total": null
            },
            "3M": {
              "price": 9.08,
              "total": null
            },
            "6M": {
              "price": 2.98,
              "total": null
            },
            "YTD": {
              "price": 4.27,
              "total": null
            },
            "1Y": {
              "price": 19.39,
              "total": 21.48
            }
          },
          "momentum": {
            "cross": "golden",
            "days_since_cross": 19,
            "sma25": 156.57,
            "sma75": 149.94,
            "rsi": 61.2,
            "rsi_state": "neutral"
          }
        },
        {
          "label": "工業",
          "ticker": "XLI",
          "review": false,
          "status": "ok",
          "as_of": "2026-07-13",
          "stale": false,
          "returns": {
            "1D": {
              "price": -0.85,
              "total": null
            },
            "1W": {
              "price": -2.8,
              "total": null
            },
            "1M": {
              "price": 2.38,
              "total": null
            },
            "3M": {
              "price": 4.42,
              "total": null
            },
            "6M": {
              "price": 9.98,
              "total": null
            },
            "YTD": {
              "price": 16.28,
              "total": null
            },
            "1Y": {
              "price": 20.09,
              "total": 21.63
            }
          },
          "momentum": {
            "cross": "golden",
            "days_since_cross": 47,
            "sma25": 179.84,
            "sma75": 173.83,
            "rsi": 51.3,
            "rsi_state": "neutral"
          }
        },
        {
          "label": "素材",
          "ticker": "XLB",
          "review": false,
          "status": "ok",
          "as_of": "2026-07-13",
          "stale": false,
          "returns": {
            "1D": {
              "price": -0.61,
              "total": null
            },
            "1W": {
              "price": -2.69,
              "total": null
            },
            "1M": {
              "price": -3.07,
              "total": null
            },
            "3M": {
              "price": -3.08,
              "total": null
            },
            "6M": {
              "price": 3.8,
              "total": null
            },
            "YTD": {
              "price": 11.53,
              "total": null
            },
            "1Y": {
              "price": 10.53,
              "total": 12.55
            }
          },
          "momentum": {
            "cross": "golden",
            "days_since_cross": 52,
            "sma25": 51.22,
            "sma75": 51.13,
            "rsi": 45.8,
            "rsi_state": "neutral"
          }
        },
        {
          "label": "テクノロジー",
          "ticker": "XLK",
          "review": false,
          "status": "ok",
          "as_of": "2026-07-13",
          "stale": false,
          "returns": {
            "1D": {
              "price": -2.42,
              "total": null
            },
            "1W": {
              "price": -1.25,
              "total": null
            },
            "1M": {
              "price": -1.9,
              "total": null
            },
            "3M": {
              "price": 24.5,
              "total": null
            },
            "6M": {
              "price": 23.76,
              "total": null
            },
            "YTD": {
              "price": 25.92,
              "total": null
            },
            "1Y": {
              "price": 41.71,
              "total": 42.45
            }
          },
          "momentum": {
            "cross": "golden",
            "days_since_cross": 54,
            "sma25": 184.37,
            "sma75": 169.54,
            "rsi": 47.9,
            "rsi_state": "neutral"
          }
        },
        {
          "label": "通信サービス",
          "ticker": "XLC",
          "review": false,
          "status": "ok",
          "as_of": "2026-07-13",
          "stale": false,
          "returns": {
            "1D": {
              "price": -0.04,
              "total": null
            },
            "1W": {
              "price": 1.25,
              "total": null
            },
            "1M": {
              "price": -0.05,
              "total": null
            },
            "3M": {
              "price": -2.81,
              "total": null
            },
            "6M": {
              "price": -4.53,
              "total": null
            },
            "YTD": {
              "price": -5.21,
              "total": null
            },
            "1Y": {
              "price": 5.26,
              "total": 6.59
            }
          },
          "momentum": {
            "cross": "dead",
            "days_since_cross": 20,
            "sma25": 109.74,
            "sma75": 113.27,
            "rsi": 54.1,
            "rsi_state": "neutral"
          }
        },
        {
          "label": "公益",
          "ticker": "XLU",
          "review": false,
          "status": "ok",
          "as_of": "2026-07-13",
          "stale": false,
          "returns": {
            "1D": {
              "price": 0.68,
              "total": null
            },
            "1W": {
              "price": 0.93,
              "total": null
            },
            "1M": {
              "price": 2.67,
              "total": null
            },
            "3M": {
              "price": -1.44,
              "total": null
            },
            "6M": {
              "price": 6.7,
              "total": null
            },
            "YTD": {
              "price": 7.1,
              "total": null
            },
            "1Y": {
              "price": 10.9,
              "total": 14.0
            }
          },
          "momentum": {
            "cross": "dead",
            "days_since_cross": 38,
            "sma25": 45.01,
            "sma75": 45.32,
            "rsi": 55.3,
            "rsi_state": "neutral"
          }
        },
        {
          "label": "不動産",
          "ticker": "XLRE",
          "review": false,
          "status": "ok",
          "as_of": "2026-07-13",
          "stale": false,
          "returns": {
            "1D": {
              "price": 0.56,
              "total": null
            },
            "1W": {
              "price": 0.93,
              "total": null
            },
            "1M": {
              "price": -1.46,
              "total": null
            },
            "3M": {
              "price": 3.91,
              "total": null
            },
            "6M": {
              "price": 9.21,
              "total": null
            },
            "YTD": {
              "price": 10.78,
              "total": null
            },
            "1Y": {
              "price": 7.53,
              "total": 11.24
            }
          },
          "momentum": {
            "cross": "golden",
            "days_since_cross": 52,
            "sma25": 44.58,
            "sma75": 43.78,
            "rsi": 52.7,
            "rsi_state": "neutral"
          }
        }
      ]
    },
    {
      "id": "commodities",
      "title": "コモディティ ETF",
      "items": [
        {
          "label": "コモディティ全般",
          "ticker": "DBC",
          "review": false,
          "status": "ok",
          "as_of": "2026-07-13",
          "stale": false,
          "returns": {
            "1D": {
              "price": 2.94,
              "total": null
            },
            "1W": {
              "price": 4.93,
              "total": null
            },
            "1M": {
              "price": -0.77,
              "total": null
            },
            "3M": {
              "price": -2.18,
              "total": null
            },
            "6M": {
              "price": 21.22,
              "total": null
            },
            "YTD": {
              "price": 26.7,
              "total": null
            },
            "1Y": {
              "price": 25.86,
              "total": 30.09
            }
          },
          "momentum": {
            "cross": "dead",
            "days_since_cross": 13,
            "sma25": 27.68,
            "sma75": 29.16,
            "rsi": 55.3,
            "rsi_state": "neutral"
          }
        },
        {
          "label": "エネルギー",
          "ticker": "DBE",
          "review": false,
          "status": "ok",
          "as_of": "2026-07-13",
          "stale": false,
          "returns": {
            "1D": {
              "price": 6.87,
              "total": null
            },
            "1W": {
              "price": 11.13,
              "total": null
            },
            "1M": {
              "price": -1.18,
              "total": null
            },
            "3M": {
              "price": -0.36,
              "total": null
            },
            "6M": {
              "price": 58.5,
              "total": null
            },
            "YTD": {
              "price": 66.03,
              "total": null
            },
            "1Y": {
              "price": 47.46,
              "total": 53.22
            }
          },
          "momentum": {
            "cross": "dead",
            "days_since_cross": 11,
            "sma25": 27.79,
            "sma75": 29.85,
            "rsi": 56.2,
            "rsi_state": "neutral"
          }
        },
        {
          "label": "天然ガス",
          "ticker": "UNG",
          "review": false,
          "status": "ok",
          "as_of": "2026-07-13",
          "stale": false,
          "returns": {
            "1D": {
              "price": -2.17,
              "total": null
            },
            "1W": {
              "price": -11.44,
              "total": null
            },
            "1M": {
              "price": -8.63,
              "total": null
            },
            "3M": {
              "price": -2.9,
              "total": null
            },
            "6M": {
              "price": -8.39,
              "total": null
            },
            "YTD": {
              "price": -15.42,
              "total": null
            },
            "1Y": {
              "price": -30.5,
              "total": -30.5
            }
          },
          "momentum": {
            "cross": "golden",
            "days_since_cross": 17,
            "sma25": 11.47,
            "sma75": 11.24,
            "rsi": 33.6,
            "rsi_state": "neutral"
          }
        },
        {
          "label": "ゴールド",
          "ticker": "GLD",
          "review": false,
          "status": "ok",
          "as_of": "2026-07-13",
          "stale": false,
          "returns": {
            "1D": {
              "price": -2.62,
              "total": null
            },
            "1W": {
              "price": -3.93,
              "total": null
            },
            "1M": {
              "price": -5.02,
              "total": null
            },
            "3M": {
              "price": -15.67,
              "total": null
            },
            "6M": {
              "price": -12.93,
              "total": null
            },
            "YTD": {
              "price": -7.36,
              "total": null
            },
            "1Y": {
              "price": 18.76,
              "total": 18.76
            }
          },
          "momentum": {
            "cross": "dead",
            "days_since_cross": 65,
            "sma25": 380.59,
            "sma75": 410.22,
            "rsi": 36.8,
            "rsi_state": "neutral"
          }
        },
        {
          "label": "シルバー",
          "ticker": "SLV",
          "review": false,
          "status": "ok",
          "as_of": "2026-07-13",
          "stale": false,
          "returns": {
            "1D": {
              "price": -3.32,
              "total": null
            },
            "1W": {
              "price": -7.04,
              "total": null
            },
            "1M": {
              "price": -14.9,
              "total": null
            },
            "3M": {
              "price": -23.61,
              "total": null
            },
            "6M": {
              "price": -33.64,
              "total": null
            },
            "YTD": {
              "price": -19.03,
              "total": null
            },
            "1Y": {
              "price": 48.9,
              "total": 48.9
            }
          },
          "momentum": {
            "cross": "dead",
            "days_since_cross": 72,
            "sma25": 56.77,
            "sma75": 64.85,
            "rsi": 35.3,
            "rsi_state": "neutral"
          }
        },
        {
          "label": "ベースメタル",
          "ticker": "DBB",
          "review": false,
          "status": "ok",
          "as_of": "2026-07-13",
          "stale": false,
          "returns": {
            "1D": {
              "price": 0.12,
              "total": null
            },
            "1W": {
              "price": 0.91,
              "total": null
            },
            "1M": {
              "price": -4.86,
              "total": null
            },
            "3M": {
              "price": -1.25,
              "total": null
            },
            "6M": {
              "price": 1.41,
              "total": null
            },
            "YTD": {
              "price": 6.71,
              "total": null
            },
            "1Y": {
              "price": 27.7,
              "total": 31.18
            }
          },
          "momentum": {
            "cross": "dead",
            "days_since_cross": 1,
            "sma25": 24.73,
            "sma75": 24.9,
            "rsi": 46.5,
            "rsi_state": "neutral"
          }
        },
        {
          "label": "農産物",
          "ticker": "DBA",
          "review": false,
          "status": "ok",
          "as_of": "2026-07-13",
          "stale": false,
          "returns": {
            "1D": {
              "price": -0.18,
              "total": null
            },
            "1W": {
              "price": 0.65,
              "total": null
            },
            "1M": {
              "price": 5.64,
              "total": null
            },
            "3M": {
              "price": 2.93,
              "total": null
            },
            "6M": {
              "price": 8.41,
              "total": null
            },
            "YTD": {
              "price": 8.62,
              "total": null
            },
            "1Y": {
              "price": 7.57,
              "total": 11.45
            }
          },
          "momentum": {
            "cross": "dead",
            "days_since_cross": 15,
            "sma25": 26.82,
            "sma75": 27.28,
            "rsi": 64.1,
            "rsi_state": "neutral"
          }
        }
      ]
    },
    {
      "id": "bonds",
      "title": "債券 ETF",
      "items": [
        {
          "label": "短期債",
          "ticker": "SHY",
          "review": false,
          "status": "ok",
          "as_of": "2026-07-13",
          "stale": false,
          "returns": {
            "1D": {
              "price": -0.11,
              "total": null
            },
            "1W": {
              "price": -0.23,
              "total": null
            },
            "1M": {
              "price": -0.34,
              "total": null
            },
            "3M": {
              "price": -0.82,
              "total": null
            },
            "6M": {
              "price": -1.28,
              "total": null
            },
            "YTD": {
              "price": -1.24,
              "total": null
            },
            "1Y": {
              "price": -0.8,
              "total": 2.86
            }
          },
          "momentum": {
            "cross": "dead",
            "days_since_cross": 79,
            "sma25": 81.98,
            "sma75": 82.2,
            "rsi": 40.0,
            "rsi_state": "neutral"
          }
        },
        {
          "label": "中期債",
          "ticker": "IEF",
          "review": false,
          "status": "ok",
          "as_of": "2026-07-13",
          "stale": false,
          "returns": {
            "1D": {
              "price": -0.36,
              "total": null
            },
            "1W": {
              "price": -0.94,
              "total": null
            },
            "1M": {
              "price": -0.94,
              "total": null
            },
            "3M": {
              "price": -2.29,
              "total": null
            },
            "6M": {
              "price": -3.13,
              "total": null
            },
            "YTD": {
              "price": -2.98,
              "total": null
            },
            "1Y": {
              "price": -1.09,
              "total": 2.77
            }
          },
          "momentum": {
            "cross": "dead",
            "days_since_cross": 72,
            "sma25": 94.11,
            "sma75": 94.57,
            "rsi": 37.9,
            "rsi_state": "neutral"
          }
        },
        {
          "label": "20年超債券",
          "ticker": "TLT",
          "review": false,
          "status": "ok",
          "as_of": "2026-07-13",
          "stale": false,
          "returns": {
            "1D": {
              "price": -0.59,
              "total": null
            },
            "1W": {
              "price": -1.73,
              "total": null
            },
            "1M": {
              "price": -2.1,
              "total": null
            },
            "3M": {
              "price": -3.2,
              "total": null
            },
            "6M": {
              "price": -4.38,
              "total": null
            },
            "YTD": {
              "price": -3.66,
              "total": null
            },
            "1Y": {
              "price": -2.12,
              "total": 2.34
            }
          },
          "momentum": {
            "cross": "dead",
            "days_since_cross": 2,
            "sma25": 85.72,
            "sma75": 85.79,
            "rsi": 34.2,
            "rsi_state": "neutral"
          }
        },
        {
          "label": "債券合計",
          "ticker": "AGG",
          "review": false,
          "status": "ok",
          "as_of": "2026-07-13",
          "stale": false,
          "returns": {
            "1D": {
              "price": -0.38,
              "total": null
            },
            "1W": {
              "price": -0.96,
              "total": null
            },
            "1M": {
              "price": -1.06,
              "total": null
            },
            "3M": {
              "price": -1.82,
              "total": null
            },
            "6M": {
              "price": -2.49,
              "total": null
            },
            "YTD": {
              "price": -2.17,
              "total": null
            },
            "1Y": {
              "price": -0.35,
              "total": 3.67
            }
          },
          "momentum": {
            "cross": "dead",
            "days_since_cross": 74,
            "sma25": 98.62,
            "sma75": 98.87,
            "rsi": 35.1,
            "rsi_state": "neutral"
          }
        },
        {
          "label": "TIPS",
          "ticker": "TIP",
          "review": false,
          "status": "ok",
          "as_of": "2026-07-13",
          "stale": false,
          "returns": {
            "1D": {
              "price": -0.2,
              "total": null
            },
            "1W": {
              "price": -0.53,
              "total": null
            },
            "1M": {
              "price": -1.55,
              "total": null
            },
            "3M": {
              "price": -3.03,
              "total": null
            },
            "6M": {
              "price": -2.15,
              "total": null
            },
            "YTD": {
              "price": -1.82,
              "total": null
            },
            "1Y": {
              "price": -1.3,
              "total": 3.09
            }
          },
          "momentum": {
            "cross": "dead",
            "days_since_cross": 28,
            "sma25": 109.0,
            "sma75": 110.26,
            "rsi": 32.9,
            "rsi_state": "neutral"
          }
        },
        {
          "label": "ハイイールド債",
          "ticker": "HYG",
          "review": false,
          "status": "ok",
          "as_of": "2026-07-13",
          "stale": false,
          "returns": {
            "1D": {
              "price": -0.24,
              "total": null
            },
            "1W": {
              "price": -0.44,
              "total": null
            },
            "1M": {
              "price": -0.53,
              "total": null
            },
            "3M": {
              "price": -0.92,
              "total": null
            },
            "6M": {
              "price": -1.88,
              "total": null
            },
            "YTD": {
              "price": -1.38,
              "total": null
            },
            "1Y": {
              "price": -0.64,
              "total": 5.36
            }
          },
          "momentum": {
            "cross": "dead",
            "days_since_cross": 7,
            "sma25": 79.79,
            "sma75": 79.9,
            "rsi": 42.2,
            "rsi_state": "neutral"
          }
        }
      ]
    },
    {
      "id": "others",
      "title": "その他 ETF",
      "items": [
        {
          "label": "Mag7",
          "ticker": "MAGS",
          "review": false,
          "status": "ok",
          "as_of": "2026-07-13",
          "stale": false,
          "returns": {
            "1D": {
              "price": -1.02,
              "total": null
            },
            "1W": {
              "price": 1.07,
              "total": null
            },
            "1M": {
              "price": 3.2,
              "total": null
            },
            "3M": {
              "price": 8.47,
              "total": null
            },
            "6M": {
              "price": 1.52,
              "total": null
            },
            "YTD": {
              "price": 1.56,
              "total": null
            },
            "1Y": {
              "price": 19.11,
              "total": 20.86
            }
          },
          "momentum": {
            "cross": "dead",
            "days_since_cross": 2,
            "sma25": 65.07,
            "sma75": 65.44,
            "rsi": 55.2,
            "rsi_state": "neutral"
          }
        },
        {
          "label": "半導体株",
          "ticker": "SOXX",
          "review": false,
          "status": "ok",
          "as_of": "2026-07-13",
          "stale": false,
          "returns": {
            "1D": {
              "price": -4.77,
              "total": null
            },
            "1W": {
              "price": -4.8,
              "total": null
            },
            "1M": {
              "price": -7.15,
              "total": null
            },
            "3M": {
              "price": 40.75,
              "total": null
            },
            "6M": {
              "price": 66.1,
              "total": null
            },
            "YTD": {
              "price": 83.83,
              "total": null
            },
            "1Y": {
              "price": 124.89,
              "total": 125.94
            }
          },
          "momentum": {
            "cross": "golden",
            "days_since_cross": 64,
            "sma25": 590.6,
            "sma75": 502.55,
            "rsi": 45.7,
            "rsi_state": "neutral"
          }
        },
        {
          "label": "メモリ株",
          "ticker": "DRAM",
          "review": false,
          "status": "ok",
          "as_of": "2026-07-13",
          "stale": false,
          "returns": {
            "1D": {
              "price": -9.11,
              "total": null
            },
            "1W": {
              "price": -11.52,
              "total": null
            },
            "1M": {
              "price": -11.86,
              "total": null
            },
            "3M": {
              "price": 70.79,
              "total": null
            },
            "6M": {
              "price": null,
              "total": null
            },
            "YTD": {
              "price": null,
              "total": null
            },
            "1Y": {
              "price": null,
              "total": null
            }
          },
          "momentum": null
        },
        {
          "label": "金鉱山株",
          "ticker": "GDX",
          "review": false,
          "status": "ok",
          "as_of": "2026-07-13",
          "stale": false,
          "returns": {
            "1D": {
              "price": -2.86,
              "total": null
            },
            "1W": {
              "price": -6.82,
              "total": null
            },
            "1M": {
              "price": -8.32,
              "total": null
            },
            "3M": {
              "price": -25.72,
              "total": null
            },
            "6M": {
              "price": -23.95,
              "total": null
            },
            "YTD": {
              "price": -14.46,
              "total": null
            },
            "1Y": {
              "price": 39.97,
              "total": 40.98
            }
          },
          "momentum": {
            "cross": "dead",
            "days_since_cross": 70,
            "sma25": 77.99,
            "sma75": 86.88,
            "rsi": 39.4,
            "rsi_state": "neutral"
          }
        },
        {
          "label": "銀鉱山株",
          "ticker": "SIL",
          "review": false,
          "status": "ok",
          "as_of": "2026-07-13",
          "stale": false,
          "returns": {
            "1D": {
              "price": -2.74,
              "total": null
            },
            "1W": {
              "price": -6.83,
              "total": null
            },
            "1M": {
              "price": -9.08,
              "total": null
            },
            "3M": {
              "price": -23.66,
              "total": null
            },
            "6M": {
              "price": -21.36,
              "total": null
            },
            "YTD": {
              "price": -11.09,
              "total": null
            },
            "1Y": {
              "price": 46.07,
              "total": 47.84
            }
          },
          "momentum": {
            "cross": "dead",
            "days_since_cross": 69,
            "sma25": 79.21,
            "sma75": 88.11,
            "rsi": 39.2,
            "rsi_state": "neutral"
          }
        }
      ]
    }
  ]
}